[{"NM_MESO":"CENTRO OCIDENTAL RIO-GRANDENSE","CD_GEOCME":"4303"},{"NM_MESO":"CENTRO ORIENTAL RIO-GRANDENSE","CD_GEOCME":"4304"},{"NM_MESO":"LAGOA MIRIM","CD_GEOCME":"4377"},{"NM_MESO":"NORDESTE RIO-GRANDENSE","CD_GEOCME":"4302"},{"NM_MESO":"SUDESTE RIO-GRANDENSE","CD_GEOCME":"4307"},{"NM_MESO":"NOROESTE RIO-GRANDENSE","CD_GEOCME":"4301"},{"NM_MESO":"LAGOA DOS PATOS","CD_GEOCME":"4388"},{"NM_MESO":"METROPOLITANA DE PORTO ALEGRE","CD_GEOCME":"4305"},{"NM_MESO":"SUDOESTE RIO-GRANDENSE","CD_GEOCME":"4306"}]