[{"NM_MICRO":"PETROLINA","CD_GEOCMI":"26005"},{"NM_MICRO":"GARANHUNS","CD_GEOCMI":"26011"},{"NM_MICRO":"FERNANDO DE NORONHA","CD_GEOCMI":"26019"},{"NM_MICRO":"ALTO CAPIBARIBE","CD_GEOCMI":"26009"},{"NM_MICRO":"SALGUEIRO","CD_GEOCMI":"26002"},{"NM_MICRO":"ITAPARICA","CD_GEOCMI":"26006"},{"NM_MICRO":"ITAMARACÁ","CD_GEOCMI":"26016"},{"NM_MICRO":"SERTÃO DO MOXOTÓ","CD_GEOCMI":"26004"},{"NM_MICRO":"VALE DO IPOJUCA","CD_GEOCMI":"26008"},{"NM_MICRO":"SUAPE","CD_GEOCMI":"26018"},{"NM_MICRO":"MATA SETENTRIONAL PERNAMBUCANA","CD_GEOCMI":"26013"},{"NM_MICRO":"MÉDIO CAPIBARIBE","CD_GEOCMI":"26010"},{"NM_MICRO":"MATA MERIDIONAL PERNAMBUCANA","CD_GEOCMI":"26015"},{"NM_MICRO":"ARARIPINA","CD_GEOCMI":"26001"},{"NM_MICRO":"PAJEÚ","CD_GEOCMI":"26003"},{"NM_MICRO":"VITÓRIA DE SANTO ANTÃO","CD_GEOCMI":"26014"},{"NM_MICRO":"RECIFE","CD_GEOCMI":"26017"},{"NM_MICRO":"VALE DO IPANEMA","CD_GEOCMI":"26007"},{"NM_MICRO":"BREJO PERNAMBUCANO","CD_GEOCMI":"26012"}]